LICENSE
MANIFEST.in
README.rst
setup.py
bin/vsi
tests/__init__.py
tests/test_api.py
tests/test_ast.py
tests/test_interpreter.py
tests/test_lexer.py
tests/test_parser.py
vsi/__init__.py
vsi/api.py
vsi/ast.py
vsi/interpreter.py
vsi/lexer.py
vsi/parser.py
vsi/utils.py
vsi.egg-info/PKG-INFO
vsi.egg-info/SOURCES.txt
vsi.egg-info/dependency_links.txt
vsi.egg-info/top_level.txt