Metadata-Version: 1.0
Name: vsi
Version: 0.1.1
Summary: very simple interpreter written in pure python
Home-page: https://github.com/afaki077/vsi
Author: Ali Faki
Author-email: alifaki077@gmail.com
License: MIT
Platform: UNKNOWN
